referencing/__init__.py
referencing/_attrs.py
referencing/_attrs.pyi
referencing/_core.py
referencing/exceptions.py
referencing/jsonschema.py
referencing/py.typed
referencing/retrieval.py
referencing/typing.py
referencing/tests/__init__.py
referencing/tests/test_core.py
referencing/tests/test_exceptions.py
referencing/tests/test_jsonschema.py
referencing/tests/test_referencing_suite.py
referencing/tests/test_retrieval.py
referencing-0.29.0.dist-info/METADATA
referencing-0.29.0.dist-info/WHEEL
referencing-0.29.0.dist-info/licenses/COPYING
referencing-0.29.0.dist-info/RECORD
