Metadata-Version: 2.1
Name: referencing
Version: 0.29.0
Summary: JSON Referencing + Python
Project-URL: Documentation, https://referencing.readthedocs.io/
Project-URL: Homepage, https://github.com/python-jsonschema/referencing
Project-URL: Issues, https://github.com/python-jsonschema/referencing/issues/
Project-URL: Funding, https://github.com/sponsors/Julian
Project-URL: Source, https://github.com/python-jsonschema/referencing
Author: Julian Berman
Author-email: Julian+referencing@GrayVines.com
License: MIT
License-File: COPYING
Keywords: asyncapi,json,jsonschema,openapi,referencing
Classifier: Development Status :: 3 - Alpha
Classifier: Intended Audience :: Developers
Classifier: License :: OSI Approved :: MIT License
Classifier: Operating System :: OS Independent
Classifier: Programming Language :: Python
Classifier: Programming Language :: Python :: 3.8
Classifier: Programming Language :: Python :: 3.9
Classifier: Programming Language :: Python :: 3.10
Classifier: Programming Language :: Python :: 3.11
Classifier: Programming Language :: Python :: Implementation :: CPython
Classifier: Programming Language :: Python :: Implementation :: PyPy
Classifier: Topic :: File Formats :: JSON
Classifier: Topic :: File Formats :: JSON :: JSON Schema
Requires-Python: >=3.8
Requires-Dist: attrs>=22.2.0
Requires-Dist: rpds-py>=0.7.0
